canvas_client/__init__.py
canvas_client/__main__.py
canvas_client/canvas_api.py
canvas_client/client.py
canvas_client/section.py
canvas_client/submission.py
canvas_client/util.py
canvas_client-0.2.1.dist-info/LICENSE
canvas_client-0.2.1.dist-info/METADATA
canvas_client-0.2.1.dist-info/WHEEL
canvas_client-0.2.1.dist-info/entry_points.txt
canvas_client-0.2.1.dist-info/top_level.txt
canvas_client-0.2.1.dist-info/RECORD
