Metadata-Version: 2.1
Name: canvas-client
Version: 0.2.1
Summary: Canvas LMS client: Download submissions, upload grades and comments from excel
Home-page: https://github.com/scsanad/canvas_client
Author: Csanad Sandor
Author-email: scsanad@cs.ubbcluj.ro
License: MIT
Platform: UNKNOWN
Classifier: License :: OSI Approved :: MIT License
Classifier: Programming Language :: Python :: 3
Classifier: Programming Language :: Python :: 3.6
Requires-Dist: jsonpickle
Requires-Dist: requests
Requires-Dist: pandas
Requires-Dist: pyunpack
Requires-Dist: xlwt
Requires-Dist: xlrd
